setup.py
src/main.py
src/instacart_roulette_daemon_client.egg-info/PKG-INFO
src/instacart_roulette_daemon_client.egg-info/SOURCES.txt
src/instacart_roulette_daemon_client.egg-info/dependency_links.txt
src/instacart_roulette_daemon_client.egg-info/top_level.txt